[{"site":"yilan","Date":"2021-09-06","Method":"GAM","Feature":"PTR","Data_Length":7,"Latitude":24.748,"Longitude":121.746,"consistency":null,"Valid_MAE":1.562,"Original_MAE":2.505,"Model":"https:\/\/github.com\/IISNRL\/DCF-PM2.5\/blob\/master\/2021\/20210906\/20210906-SPS30-yilan.joblib","Config":"https:\/\/github.com\/IISNRL\/DCF-PM2.5\/blob\/master\/2021\/20210906\/20210906-SPS30-yilan.json","Version":"2021-09-06 00:02:40","Config_FileName":"20210906-SPS30-yilan.json","Model_FileName":"20210906-SPS30-yilan.joblib"},{"site":"hengchun","Date":"2021-09-06","Method":"BayesianRidge","Feature":"P","Data_Length":30,"Latitude":21.958,"Longitude":120.789,"consistency":null,"Valid_MAE":2.498,"Original_MAE":2.466,"Model":"https:\/\/github.com\/IISNRL\/DCF-PM2.5\/blob\/master\/2021\/20210906\/20210906-SPS30-hengchun.joblib","Config":"https:\/\/github.com\/IISNRL\/DCF-PM2.5\/blob\/master\/2021\/20210906\/20210906-SPS30-hengchun.json","Version":"2021-09-06 00:02:45","Config_FileName":"20210906-SPS30-hengchun.json","Model_FileName":"20210906-SPS30-hengchun.joblib"},{"site":"zhudong","Date":"2021-09-06","Method":"GAM","Feature":"PTR","Data_Length":7,"Latitude":24.741,"Longitude":121.089,"consistency":null,"Valid_MAE":2.031,"Original_MAE":2.977,"Model":"https:\/\/github.com\/IISNRL\/DCF-PM2.5\/blob\/master\/2021\/20210906\/20210906-SPS30-zhudong.joblib","Config":"https:\/\/github.com\/IISNRL\/DCF-PM2.5\/blob\/master\/2021\/20210906\/20210906-SPS30-zhudong.json","Version":"2021-09-06 00:02:50","Config_FileName":"20210906-SPS30-zhudong.json","Model_FileName":"20210906-SPS30-zhudong.joblib"},{"site":"taoyuan","Date":"2021-09-06","Method":"GAM","Feature":"PHR","Data_Length":21,"Latitude":24.995,"Longitude":121.304,"consistency":null,"Valid_MAE":2.523,"Original_MAE":4.004,"Model":"https:\/\/github.com\/IISNRL\/DCF-PM2.5\/blob\/master\/2021\/20210906\/20210906-SPS30-taoyuan.joblib","Config":"https:\/\/github.com\/IISNRL\/DCF-PM2.5\/blob\/master\/2021\/20210906\/20210906-SPS30-taoyuan.json","Version":"2021-09-06 00:02:57","Config_FileName":"20210906-SPS30-taoyuan.json","Model_FileName":"20210906-SPS30-taoyuan.joblib"},{"site":"zhongming","Date":"2021-09-06","Method":"RidgeRegression","Feature":"P","Data_Length":30,"Latitude":24.152,"Longitude":120.641,"consistency":null,"Valid_MAE":2.092,"Original_MAE":3.131,"Model":"https:\/\/github.com\/IISNRL\/DCF-PM2.5\/blob\/master\/2021\/20210906\/20210906-SPS30-zhongming.joblib","Config":"https:\/\/github.com\/IISNRL\/DCF-PM2.5\/blob\/master\/2021\/20210906\/20210906-SPS30-zhongming.json","Version":"2021-09-06 00:03:04","Config_FileName":"20210906-SPS30-zhongming.json","Model_FileName":"20210906-SPS30-zhongming.joblib"},{"site":"yangming","Date":"2021-09-06","Method":"SVR","Feature":"PHR","Data_Length":7,"Latitude":25.183,"Longitude":121.53,"consistency":null,"Valid_MAE":1.707,"Original_MAE":4.181,"Model":"https:\/\/github.com\/IISNRL\/DCF-PM2.5\/blob\/master\/2021\/20210906\/20210906-SPS30-yangming.joblib","Config":"https:\/\/github.com\/IISNRL\/DCF-PM2.5\/blob\/master\/2021\/20210906\/20210906-SPS30-yangming.json","Version":"2021-09-06 00:03:08","Config_FileName":"20210906-SPS30-yangming.json","Model_FileName":"20210906-SPS30-yangming.joblib"},{"site":"shilin","Date":"2021-09-06","Method":"GAM","Feature":"PHT","Data_Length":7,"Latitude":25.105,"Longitude":121.515,"consistency":null,"Valid_MAE":3.406,"Original_MAE":2.465,"Model":"https:\/\/github.com\/IISNRL\/DCF-PM2.5\/blob\/master\/2021\/20210906\/20210906-SPS30-shilin.joblib","Config":"https:\/\/github.com\/IISNRL\/DCF-PM2.5\/blob\/master\/2021\/20210906\/20210906-SPS30-shilin.json","Version":"2021-09-06 00:03:13","Config_FileName":"20210906-SPS30-shilin.json","Model_FileName":"20210906-SPS30-shilin.joblib"},{"site":"miaoli","Date":"2021-09-06","Method":"GAM","Feature":"PHTR","Data_Length":30,"Latitude":24.565,"Longitude":120.82,"consistency":null,"Valid_MAE":1.938,"Original_MAE":2.558,"Model":"https:\/\/github.com\/IISNRL\/DCF-PM2.5\/blob\/master\/2021\/20210906\/20210906-SPS30-miaoli.joblib","Config":"https:\/\/github.com\/IISNRL\/DCF-PM2.5\/blob\/master\/2021\/20210906\/20210906-SPS30-miaoli.json","Version":"2021-09-06 00:03:19","Config_FileName":"20210906-SPS30-miaoli.json","Model_FileName":"20210906-SPS30-miaoli.joblib"}]