[{"site":"nantou","Date":"2020-12-13","Method":"SVR","Feature":"PHR","Data_Length":30,"Latitude":23.913,"Longitude":120.685,"consistency":0.999,"Valid_MAE":3.327,"Original_MAE":10.564,"Model":"https:\/\/github.com\/IISNRL\/DCF-PM2.5\/blob\/master\/2020\/20201213\/20201213-PMS5003-nantou.joblib","Config":"https:\/\/github.com\/IISNRL\/DCF-PM2.5\/blob\/master\/2020\/20201213\/20201213-PMS5003-nantou.json","Version":"2020-12-13 00:19:03","Config_FileName":"20201213-PMS5003-nantou.json","Model_FileName":"20201213-PMS5003-nantou.joblib"},{"site":"chiayi","Date":"2020-12-13","Method":"GAM","Feature":"PHR","Data_Length":14,"Latitude":23.463,"Longitude":120.441,"consistency":0.999,"Valid_MAE":5.662,"Original_MAE":14.52,"Model":"https:\/\/github.com\/IISNRL\/DCF-PM2.5\/blob\/master\/2020\/20201213\/20201213-PMS5003-chiayi.joblib","Config":"https:\/\/github.com\/IISNRL\/DCF-PM2.5\/blob\/master\/2020\/20201213\/20201213-PMS5003-chiayi.json","Version":"2020-12-13 00:19:14","Config_FileName":"20201213-PMS5003-chiayi.json","Model_FileName":"20201213-PMS5003-chiayi.joblib"},{"site":"puzi","Date":"2020-12-13","Method":"GAM","Feature":"PR","Data_Length":14,"Latitude":23.467,"Longitude":120.248,"consistency":0.999,"Valid_MAE":3.875,"Original_MAE":9.086,"Model":"https:\/\/github.com\/IISNRL\/DCF-PM2.5\/blob\/master\/2020\/20201213\/20201213-PMS5003-puzi.joblib","Config":"https:\/\/github.com\/IISNRL\/DCF-PM2.5\/blob\/master\/2020\/20201213\/20201213-PMS5003-puzi.json","Version":"2020-12-13 00:19:29","Config_FileName":"20201213-PMS5003-puzi.json","Model_FileName":"20201213-PMS5003-puzi.joblib"},{"site":"keelung","Date":"2020-12-13","Method":"GAM","Feature":"PHT","Data_Length":30,"Latitude":25.129,"Longitude":121.76,"consistency":0.999,"Valid_MAE":2.739,"Original_MAE":6.714,"Model":"https:\/\/github.com\/IISNRL\/DCF-PM2.5\/blob\/master\/2020\/20201213\/20201213-PMS5003-keelung.joblib","Config":"https:\/\/github.com\/IISNRL\/DCF-PM2.5\/blob\/master\/2020\/20201213\/20201213-PMS5003-keelung.json","Version":"2020-12-13 00:19:46","Config_FileName":"20201213-PMS5003-keelung.json","Model_FileName":"20201213-PMS5003-keelung.joblib"},{"site":"yilan","Date":"2020-12-13","Method":"GAM","Feature":"PHTR","Data_Length":21,"Latitude":24.748,"Longitude":121.746,"consistency":0.003,"Valid_MAE":2.616,"Original_MAE":68.721,"Model":"https:\/\/github.com\/IISNRL\/DCF-PM2.5\/blob\/master\/2020\/20201213\/20201213-PMS5003-yilan.joblib","Config":"https:\/\/github.com\/IISNRL\/DCF-PM2.5\/blob\/master\/2020\/20201213\/20201213-PMS5003-yilan.json","Version":"2020-12-13 00:20:09","Config_FileName":"20201213-PMS5003-yilan.json","Model_FileName":"20201213-PMS5003-yilan.joblib"},{"site":"hengchun","Date":"2020-12-13","Method":"LinearRegression","Feature":"PHT","Data_Length":7,"Latitude":21.958,"Longitude":120.789,"consistency":0.629,"Valid_MAE":1.395,"Original_MAE":3.304,"Model":"https:\/\/github.com\/IISNRL\/DCF-PM2.5\/blob\/master\/2020\/20201213\/20201213-PMS5003-hengchun.joblib","Config":"https:\/\/github.com\/IISNRL\/DCF-PM2.5\/blob\/master\/2020\/20201213\/20201213-PMS5003-hengchun.json","Version":"2020-12-13 00:20:44","Config_FileName":"20201213-PMS5003-hengchun.json","Model_FileName":"20201213-PMS5003-hengchun.joblib"},{"site":"pingtung","Date":"2020-12-13","Method":"GAM","Feature":"PTR","Data_Length":14,"Latitude":22.673,"Longitude":120.488,"consistency":0.989,"Valid_MAE":3.756,"Original_MAE":18.707,"Model":"https:\/\/github.com\/IISNRL\/DCF-PM2.5\/blob\/master\/2020\/20201213\/20201213-PMS5003-pingtung.joblib","Config":"https:\/\/github.com\/IISNRL\/DCF-PM2.5\/blob\/master\/2020\/20201213\/20201213-PMS5003-pingtung.json","Version":"2020-12-13 00:21:05","Config_FileName":"20201213-PMS5003-pingtung.json","Model_FileName":"20201213-PMS5003-pingtung.joblib"},{"site":"changhua","Date":"2020-12-13","Method":"SVR","Feature":"PH","Data_Length":30,"Latitude":24.066,"Longitude":120.542,"consistency":0.993,"Valid_MAE":3.091,"Original_MAE":8.917,"Model":"https:\/\/github.com\/IISNRL\/DCF-PM2.5\/blob\/master\/2020\/20201213\/20201213-PMS5003-changhua.joblib","Config":"https:\/\/github.com\/IISNRL\/DCF-PM2.5\/blob\/master\/2020\/20201213\/20201213-PMS5003-changhua.json","Version":"2020-12-13 00:21:33","Config_FileName":"20201213-PMS5003-changhua.json","Model_FileName":"20201213-PMS5003-changhua.joblib"},{"site":"banqiao","Date":"2020-12-13","Method":"SVR","Feature":"PTR","Data_Length":30,"Latitude":25.013,"Longitude":121.459,"consistency":0.979,"Valid_MAE":2.261,"Original_MAE":5.116,"Model":"https:\/\/github.com\/IISNRL\/DCF-PM2.5\/blob\/master\/2020\/20201213\/20201213-PMS5003-banqiao.joblib","Config":"https:\/\/github.com\/IISNRL\/DCF-PM2.5\/blob\/master\/2020\/20201213\/20201213-PMS5003-banqiao.json","Version":"2020-12-13 00:21:56","Config_FileName":"20201213-PMS5003-banqiao.json","Model_FileName":"20201213-PMS5003-banqiao.joblib"},{"site":"xizhi","Date":"2020-12-13","Method":"GAM","Feature":"PH","Data_Length":21,"Latitude":25.067,"Longitude":121.642,"consistency":0.999,"Valid_MAE":1.931,"Original_MAE":5.983,"Model":"https:\/\/github.com\/IISNRL\/DCF-PM2.5\/blob\/master\/2020\/20201213\/20201213-PMS5003-xizhi.joblib","Config":"https:\/\/github.com\/IISNRL\/DCF-PM2.5\/blob\/master\/2020\/20201213\/20201213-PMS5003-xizhi.json","Version":"2020-12-13 00:22:23","Config_FileName":"20201213-PMS5003-xizhi.json","Model_FileName":"20201213-PMS5003-xizhi.joblib"},{"site":"hsinchu","Date":"2020-12-13","Method":"GAM","Feature":"PT","Data_Length":30,"Latitude":24.806,"Longitude":120.972,"consistency":0.658,"Valid_MAE":3.284,"Original_MAE":11.022,"Model":"https:\/\/github.com\/IISNRL\/DCF-PM2.5\/blob\/master\/2020\/20201213\/20201213-PMS5003-hsinchu.joblib","Config":"https:\/\/github.com\/IISNRL\/DCF-PM2.5\/blob\/master\/2020\/20201213\/20201213-PMS5003-hsinchu.json","Version":"2020-12-13 00:22:49","Config_FileName":"20201213-PMS5003-hsinchu.json","Model_FileName":"20201213-PMS5003-hsinchu.joblib"},{"site":"zhudong","Date":"2020-12-13","Method":"SVR","Feature":"PHR","Data_Length":30,"Latitude":24.741,"Longitude":121.089,"consistency":0.99,"Valid_MAE":1.831,"Original_MAE":6.325,"Model":"https:\/\/github.com\/IISNRL\/DCF-PM2.5\/blob\/master\/2020\/20201213\/20201213-PMS5003-zhudong.joblib","Config":"https:\/\/github.com\/IISNRL\/DCF-PM2.5\/blob\/master\/2020\/20201213\/20201213-PMS5003-zhudong.json","Version":"2020-12-13 00:23:12","Config_FileName":"20201213-PMS5003-zhudong.json","Model_FileName":"20201213-PMS5003-zhudong.joblib"},{"site":"pingzhen","Date":"2020-12-13","Method":"RidgeRegression","Feature":"PHTR","Data_Length":30,"Latitude":24.953,"Longitude":121.204,"consistency":0.992,"Valid_MAE":3.018,"Original_MAE":2.783,"Model":"https:\/\/github.com\/IISNRL\/DCF-PM2.5\/blob\/master\/2020\/20201213\/20201213-PMS5003-pingzhen.joblib","Config":"https:\/\/github.com\/IISNRL\/DCF-PM2.5\/blob\/master\/2020\/20201213\/20201213-PMS5003-pingzhen.json","Version":"2020-12-13 00:23:23","Config_FileName":"20201213-PMS5003-pingzhen.json","Model_FileName":"20201213-PMS5003-pingzhen.joblib"},{"site":"taoyuan","Date":"2020-12-13","Method":"SVR","Feature":"PR","Data_Length":30,"Latitude":24.995,"Longitude":121.304,"consistency":0.997,"Valid_MAE":2.146,"Original_MAE":6.533,"Model":"https:\/\/github.com\/IISNRL\/DCF-PM2.5\/blob\/master\/2020\/20201213\/20201213-PMS5003-taoyuan.joblib","Config":"https:\/\/github.com\/IISNRL\/DCF-PM2.5\/blob\/master\/2020\/20201213\/20201213-PMS5003-taoyuan.json","Version":"2020-12-13 00:23:41","Config_FileName":"20201213-PMS5003-taoyuan.json","Model_FileName":"20201213-PMS5003-taoyuan.joblib"},{"site":"magong","Date":"2020-12-13","Method":"LinearRegression","Feature":"P","Data_Length":30,"Latitude":23.569,"Longitude":119.566,"consistency":0.992,"Valid_MAE":2.446,"Original_MAE":4.905,"Model":"https:\/\/github.com\/IISNRL\/DCF-PM2.5\/blob\/master\/2020\/20201213\/20201213-PMS5003-magong.joblib","Config":"https:\/\/github.com\/IISNRL\/DCF-PM2.5\/blob\/master\/2020\/20201213\/20201213-PMS5003-magong.json","Version":"2020-12-13 00:24:01","Config_FileName":"20201213-PMS5003-magong.json","Model_FileName":"20201213-PMS5003-magong.joblib"},{"site":"zhongming","Date":"2020-12-13","Method":"GAM","Feature":"P","Data_Length":30,"Latitude":24.152,"Longitude":120.641,"consistency":0.999,"Valid_MAE":3.375,"Original_MAE":8.371,"Model":"https:\/\/github.com\/IISNRL\/DCF-PM2.5\/blob\/master\/2020\/20201213\/20201213-PMS5003-zhongming.joblib","Config":"https:\/\/github.com\/IISNRL\/DCF-PM2.5\/blob\/master\/2020\/20201213\/20201213-PMS5003-zhongming.json","Version":"2020-12-13 00:24:14","Config_FileName":"20201213-PMS5003-zhongming.json","Model_FileName":"20201213-PMS5003-zhongming.joblib"},{"site":"fengyuan","Date":"2020-12-13","Method":"BayesianRidge","Feature":"PHT","Data_Length":30,"Latitude":24.257,"Longitude":120.742,"consistency":0.995,"Valid_MAE":3.564,"Original_MAE":8.602,"Model":"https:\/\/github.com\/IISNRL\/DCF-PM2.5\/blob\/master\/2020\/20201213\/20201213-PMS5003-fengyuan.joblib","Config":"https:\/\/github.com\/IISNRL\/DCF-PM2.5\/blob\/master\/2020\/20201213\/20201213-PMS5003-fengyuan.json","Version":"2020-12-13 00:24:28","Config_FileName":"20201213-PMS5003-fengyuan.json","Model_FileName":"20201213-PMS5003-fengyuan.joblib"},{"site":"yangming","Date":"2020-12-13","Method":"GAM","Feature":"PH","Data_Length":30,"Latitude":25.183,"Longitude":121.53,"consistency":null,"Valid_MAE":2.269,"Original_MAE":6.756,"Model":"https:\/\/github.com\/IISNRL\/DCF-PM2.5\/blob\/master\/2020\/20201213\/20201213-PMS5003-yangming.joblib","Config":"https:\/\/github.com\/IISNRL\/DCF-PM2.5\/blob\/master\/2020\/20201213\/20201213-PMS5003-yangming.json","Version":"2020-12-13 00:24:46","Config_FileName":"20201213-PMS5003-yangming.json","Model_FileName":"20201213-PMS5003-yangming.joblib"},{"site":"wanhua","Date":"2020-12-13","Method":"GAM","Feature":"PR","Data_Length":21,"Latitude":25.047,"Longitude":121.508,"consistency":0.996,"Valid_MAE":2.303,"Original_MAE":4.41,"Model":"https:\/\/github.com\/IISNRL\/DCF-PM2.5\/blob\/master\/2020\/20201213\/20201213-PMS5003-wanhua.joblib","Config":"https:\/\/github.com\/IISNRL\/DCF-PM2.5\/blob\/master\/2020\/20201213\/20201213-PMS5003-wanhua.json","Version":"2020-12-13 00:25:07","Config_FileName":"20201213-PMS5003-wanhua.json","Model_FileName":"20201213-PMS5003-wanhua.joblib"},{"site":"shilin","Date":"2020-12-13","Method":"BayesianRidge","Feature":"PHR","Data_Length":30,"Latitude":25.105,"Longitude":121.515,"consistency":0.999,"Valid_MAE":2.114,"Original_MAE":4.099,"Model":"https:\/\/github.com\/IISNRL\/DCF-PM2.5\/blob\/master\/2020\/20201213\/20201213-PMS5003-shilin.joblib","Config":"https:\/\/github.com\/IISNRL\/DCF-PM2.5\/blob\/master\/2020\/20201213\/20201213-PMS5003-shilin.json","Version":"2020-12-13 00:25:28","Config_FileName":"20201213-PMS5003-shilin.json","Model_FileName":"20201213-PMS5003-shilin.joblib"},{"site":"tainan","Date":"2020-12-13","Method":"GAM","Feature":"PHR","Data_Length":21,"Latitude":22.985,"Longitude":120.203,"consistency":0.998,"Valid_MAE":3.176,"Original_MAE":13.4,"Model":"https:\/\/github.com\/IISNRL\/DCF-PM2.5\/blob\/master\/2020\/20201213\/20201213-PMS5003-tainan.joblib","Config":"https:\/\/github.com\/IISNRL\/DCF-PM2.5\/blob\/master\/2020\/20201213\/20201213-PMS5003-tainan.json","Version":"2020-12-13 00:25:50","Config_FileName":"20201213-PMS5003-tainan.json","Model_FileName":"20201213-PMS5003-tainan.joblib"},{"site":"xinying","Date":"2020-12-13","Method":"GAM","Feature":"PR","Data_Length":30,"Latitude":23.306,"Longitude":120.317,"consistency":0.993,"Valid_MAE":5.015,"Original_MAE":8.66,"Model":"https:\/\/github.com\/IISNRL\/DCF-PM2.5\/blob\/master\/2020\/20201213\/20201213-PMS5003-xinying.joblib","Config":"https:\/\/github.com\/IISNRL\/DCF-PM2.5\/blob\/master\/2020\/20201213\/20201213-PMS5003-xinying.json","Version":"2020-12-13 00:26:16","Config_FileName":"20201213-PMS5003-xinying.json","Model_FileName":"20201213-PMS5003-xinying.joblib"},{"site":"taitung","Date":"2020-12-13","Method":"RandomForestRegressor","Feature":"PHTR","Data_Length":30,"Latitude":22.755,"Longitude":121.15,"consistency":null,"Valid_MAE":2.244,"Original_MAE":4.114,"Model":"https:\/\/github.com\/IISNRL\/DCF-PM2.5\/blob\/master\/2020\/20201213\/20201213-PMS5003-taitung.joblib","Config":"https:\/\/github.com\/IISNRL\/DCF-PM2.5\/blob\/master\/2020\/20201213\/20201213-PMS5003-taitung.json","Version":"2020-12-13 00:26:49","Config_FileName":"20201213-PMS5003-taitung.json","Model_FileName":"20201213-PMS5003-taitung.joblib"},{"site":"hualien","Date":"2020-12-13","Method":"BayesianRidge","Feature":"PHR","Data_Length":30,"Latitude":23.971,"Longitude":121.6,"consistency":0.45,"Valid_MAE":2.585,"Original_MAE":4.825,"Model":"https:\/\/github.com\/IISNRL\/DCF-PM2.5\/blob\/master\/2020\/20201213\/20201213-PMS5003-hualien.joblib","Config":"https:\/\/github.com\/IISNRL\/DCF-PM2.5\/blob\/master\/2020\/20201213\/20201213-PMS5003-hualien.json","Version":"2020-12-13 00:27:59","Config_FileName":"20201213-PMS5003-hualien.json","Model_FileName":"20201213-PMS5003-hualien.joblib"},{"site":"sanyi","Date":"2020-12-13","Method":"SVR","Feature":"PHR","Data_Length":30,"Latitude":24.383,"Longitude":120.759,"consistency":0.998,"Valid_MAE":3.424,"Original_MAE":10.823,"Model":"https:\/\/github.com\/IISNRL\/DCF-PM2.5\/blob\/master\/2020\/20201213\/20201213-PMS5003-sanyi.joblib","Config":"https:\/\/github.com\/IISNRL\/DCF-PM2.5\/blob\/master\/2020\/20201213\/20201213-PMS5003-sanyi.json","Version":"2020-12-13 00:28:18","Config_FileName":"20201213-PMS5003-sanyi.json","Model_FileName":"20201213-PMS5003-sanyi.joblib"},{"site":"miaoli","Date":"2020-12-13","Method":"SVR","Feature":"P","Data_Length":30,"Latitude":24.565,"Longitude":120.82,"consistency":0.999,"Valid_MAE":2.712,"Original_MAE":7.337,"Model":"https:\/\/github.com\/IISNRL\/DCF-PM2.5\/blob\/master\/2020\/20201213\/20201213-PMS5003-miaoli.joblib","Config":"https:\/\/github.com\/IISNRL\/DCF-PM2.5\/blob\/master\/2020\/20201213\/20201213-PMS5003-miaoli.json","Version":"2020-12-13 00:28:44","Config_FileName":"20201213-PMS5003-miaoli.json","Model_FileName":"20201213-PMS5003-miaoli.joblib"},{"site":"matsu","Date":"2020-12-13","Method":"RidgeRegression","Feature":"PTR","Data_Length":7,"Latitude":26.16,"Longitude":119.95,"consistency":0.998,"Valid_MAE":4.956,"Original_MAE":10.249,"Model":"https:\/\/github.com\/IISNRL\/DCF-PM2.5\/blob\/master\/2020\/20201213\/20201213-PMS5003-matsu.joblib","Config":"https:\/\/github.com\/IISNRL\/DCF-PM2.5\/blob\/master\/2020\/20201213\/20201213-PMS5003-matsu.json","Version":"2020-12-13 00:29:06","Config_FileName":"20201213-PMS5003-matsu.json","Model_FileName":"20201213-PMS5003-matsu.joblib"},{"site":"kinmen","Date":"2020-12-13","Method":"GAM","Feature":"PR","Data_Length":14,"Latitude":24.432,"Longitude":118.312,"consistency":0.997,"Valid_MAE":3.541,"Original_MAE":12.152,"Model":"https:\/\/github.com\/IISNRL\/DCF-PM2.5\/blob\/master\/2020\/20201213\/20201213-PMS5003-kinmen.joblib","Config":"https:\/\/github.com\/IISNRL\/DCF-PM2.5\/blob\/master\/2020\/20201213\/20201213-PMS5003-kinmen.json","Version":"2020-12-13 00:29:20","Config_FileName":"20201213-PMS5003-kinmen.json","Model_FileName":"20201213-PMS5003-kinmen.joblib"},{"site":"douliu","Date":"2020-12-13","Method":"SVR","Feature":"P","Data_Length":14,"Latitude":23.712,"Longitude":120.545,"consistency":0.996,"Valid_MAE":5.118,"Original_MAE":9.133,"Model":"https:\/\/github.com\/IISNRL\/DCF-PM2.5\/blob\/master\/2020\/20201213\/20201213-PMS5003-douliu.joblib","Config":"https:\/\/github.com\/IISNRL\/DCF-PM2.5\/blob\/master\/2020\/20201213\/20201213-PMS5003-douliu.json","Version":"2020-12-13 00:29:32","Config_FileName":"20201213-PMS5003-douliu.json","Model_FileName":"20201213-PMS5003-douliu.joblib"},{"site":"qianjin","Date":"2020-12-13","Method":"RandomForestRegressor","Feature":"PR","Data_Length":30,"Latitude":22.633,"Longitude":120.288,"consistency":0.984,"Valid_MAE":3.898,"Original_MAE":13.58,"Model":"https:\/\/github.com\/IISNRL\/DCF-PM2.5\/blob\/master\/2020\/20201213\/20201213-PMS5003-qianjin.joblib","Config":"https:\/\/github.com\/IISNRL\/DCF-PM2.5\/blob\/master\/2020\/20201213\/20201213-PMS5003-qianjin.json","Version":"2020-12-13 00:29:43","Config_FileName":"20201213-PMS5003-qianjin.json","Model_FileName":"20201213-PMS5003-qianjin.joblib"},{"site":"meinong","Date":"2020-12-13","Method":"GAM","Feature":"PR","Data_Length":30,"Latitude":22.884,"Longitude":120.531,"consistency":0.996,"Valid_MAE":2.894,"Original_MAE":16.8,"Model":"https:\/\/github.com\/IISNRL\/DCF-PM2.5\/blob\/master\/2020\/20201213\/20201213-PMS5003-meinong.joblib","Config":"https:\/\/github.com\/IISNRL\/DCF-PM2.5\/blob\/master\/2020\/20201213\/20201213-PMS5003-meinong.json","Version":"2020-12-13 00:30:24","Config_FileName":"20201213-PMS5003-meinong.json","Model_FileName":"20201213-PMS5003-meinong.joblib"}]